shortrate/__init__.py
shortrate/hullwhite_model.py
shortrate/hullwhite_multicurrency_model.py
shortrate/market_risk_factor.py
shortrate/risk_factor_model.py
shortrate-0.3.dist-info/LICENSE
shortrate-0.3.dist-info/METADATA
shortrate-0.3.dist-info/WHEEL
shortrate-0.3.dist-info/top_level.txt
shortrate-0.3.dist-info/RECORD
